CHANGELOG.md
LICENSE
MANIFEST.in
README.md
requirements.txt
setup.cfg
setup.py
bin/portunus
portunus/VERSION
portunus/__init__.py
portunus/faucetrpc.py
portunus/portunus.py
portunus/validators.py
portunus.egg-info/PKG-INFO
portunus.egg-info/SOURCES.txt
portunus.egg-info/dependency_links.txt
portunus.egg-info/requires.txt
portunus.egg-info/top_level.txt
portunus/tests/__init__.py
portunus/tests/helpers.py
portunus/tests/test_portunus.py
portunus/tests/test_validators.py