Metadata-Version: 1.2
Name: portunus
Version: 0.2.2
Summary: A platform for multi-tenant environments.
Home-page: https://github.com/IQTLabs/portunus
Author: cglewis
Author-email: clewis@iqt.org
Maintainer: cglewis
Maintainer-email: clewis@iqt.org
License: Apache License 2.0
Keywords: multi-tenant network analysis utilities
Platform: UNKNOWN
